{
    "sabonete":{
        "nome": "Sabonete corporal limpa e perfuma - vegano ",
        "id": "6398",
        "valor": 7.00,
        "estoque": "Disponível"
    },

    "shampoo":{
        "nome": "Shampoo em barra limpeza profunda",
        "id": "1452",
        "valor": 12.00,
        "estoque": "Disponível"
    },

    "condicionador":{
        "nome": "condicionador em barra vegano  - 40g",
        "id": "9874",
        "valor": 13.00,
        "estoque": "Disponível"
    },

    "kit1":{
        "nome": "Kit beleza natural - Shampoo, condicionador e óleo corporal",
        "id": "6547",
        "valor": 24.00,
        "estoque": "Disponível"
    },
    "argila":{
        "nome": "Argila Verde - 200g",
        "id": "4312",
        "valor": 8.00,
        "estoque": "Disponível"
    },

    "oleo":{
        "nome": "Óleo de malaleuca para a pele - 100g",
        "id": "1234",
        "valor": 11.00,
        "estoque": "Disponível"
    },

    "kit2":{
        "nome": "Sabonete de Maracujá",
        "id": "1111",
        "valor": 21.00,
        "estoque": "Disponível"
    },

    "essencia":{
        "nome": "Sabone de Rosas",
        "id": "2211",
        "valor": 9.00,
        "estoque": "Disponível"
    },

    "escova":{
        "nome": "Óleo de Lavanda",
        "id": "3534",
        "valor": 7.00,
        "estoque": "Disponível"
    },

    "argilaRosa":{
        "nome": "Argila rosa",
        "id": "8201",
        "valor": 8.00,
        "estoque": "Disponível"
    },

    "serum":{
        "nome": "Serum",
        "id": "5327",
        "valor": 10.00,
        "estoque": "Disponível"
    },

    "oleoEssencial":{
        "nome": "Sabonete de Mamão",
        "id": "7128",
        "valor": 9.00,
        "estoque": "Disponível"
    }
}
